dagster_meltano/__init__.py
dagster_meltano/exceptions.py
dagster_meltano/generation.py
dagster_meltano/job.py
dagster_meltano/logging.yaml
dagster_meltano/meltano_resource.py
dagster_meltano/ops.py
dagster_meltano/schedule.py
dagster_meltano/utils.py
elt_dagster_meltano-1.0.0.dist-info/METADATA
elt_dagster_meltano-1.0.0.dist-info/WHEEL
elt_dagster_meltano-1.0.0.dist-info/licenses/LICENSE
elt_dagster_meltano-1.0.0.dist-info/RECORD
