Metadata-Version: 2.4
Name: elt-dagster-meltano
Version: 1.0.0
Summary: A dagster plugin that allows you to run your Meltano project inside Dagster.
License: Apache 2.0
License-File: LICENSE
Author: Camis Inc
Requires-Python: >=3.9,<3.14
Classifier: License :: Other/Proprietary License
Classifier: Programming Language :: Python :: 3
Classifier: Programming Language :: Python :: 3.9
Classifier: Programming Language :: Python :: 3.10
Classifier: Programming Language :: Python :: 3.11
Classifier: Programming Language :: Python :: 3.12
Classifier: Programming Language :: Python :: 3.13
Requires-Dist: dagster (>=1.10,<2)
Project-URL: Homepage, https://github.com/camisinc/elt-dagster-meltano
